README.md
setup.py
monome/__init__.py
monome/device.py
monome/event.py
monome/exceptions.py
monome/serialosc.py
monome/signalflow.py
monome/utils.py
monome.egg-info/PKG-INFO
monome.egg-info/SOURCES.txt
monome.egg-info/dependency_links.txt
monome.egg-info/requires.txt
monome.egg-info/top_level.txt
monome/arc/__init__.py
monome/arc/arc.py
monome/arc/event.py
monome/arc/arcui/__init__.py
monome/arc/arcui/__main__.py
monome/arc/arcui/arcui.py
monome/arc/arcui/event.py
monome/arc/arcui/page.py
monome/arc/arcui/ring/__init__.py
monome/arc/arcui/ring/angular.py
monome/arc/arcui/ring/base.py
monome/arc/arcui/ring/bipolar.py
monome/arc/arcui/ring/reel.py
monome/arc/arcui/ring/unipolar.py
monome/grid/__init__.py
monome/grid/event.py
monome/grid/grid.py
monome/grid/ui.py
monome/grid/page/__init__.py
monome/grid/page/freeform.py
monome/grid/page/keyboard.py
monome/grid/page/levels.py
monome/grid/page/page.py
monome/grid/page/scale_matrix.py