Metadata-Version: 2.1
Name: monome
Version: 0.1.0
Summary: Synchronous I/O for monome devices
Home-page: https://github.com/ideoforms/monome
Author: Daniel Jones
Author-email: dan-code@erase.net
Keywords: audio,sound,music,control,monome,grid,arc
Classifier: Topic :: Multimedia :: Sound/Audio
Classifier: Topic :: Artistic Software
Classifier: Topic :: Communications
Classifier: Development Status :: 3 - Alpha
Classifier: Intended Audience :: Developers
